openrouter_manager/__init__.py
openrouter_manager/adapter/ai_agent.py
openrouter_manager/adapter/llm_exception.py
openrouter_manager/adapter/prompt.py
openrouter_manager/adapter/variable.py
openrouter_manager-0.1.0.dist-info/LICENSE.txt
openrouter_manager-0.1.0.dist-info/METADATA
openrouter_manager-0.1.0.dist-info/WHEEL
openrouter_manager-0.1.0.dist-info/top_level.txt
openrouter_manager-0.1.0.dist-info/RECORD
