Metadata-Version: 2.2
Name: openrouter_manager
Version: 0.1.0
Summary: Wrapper library for using **DeepSeek** with **openrouter.ai**
Home-page: https://bitbucket.org/koralatpm/openrouter-manager/
Author: Lenin Lozano
Author-email: lenin@koralat.co
License: MIT
Project-URL: Documentation, https://bitbucket.org/koralatpm/openrouter-manager/
Project-URL: Source, https://bitbucket.org/koralatpm/openrouter-manager/src/main/
Project-URL: Changelog, https://bitbucket.org/koralatpm/openrouter-manager/src/main/CHANGELOG.rst
Platform: any
Classifier: Development Status :: 3 - Alpha
Classifier: Programming Language :: Python
Classifier: Environment :: Plugins
Classifier: Framework :: tox
Classifier: Framework :: Pytest
Classifier: Intended Audience :: Developers
Classifier: License :: OSI Approved :: MIT License
License-File: LICENSE.txt
Requires-Dist: importlib-metadata; python_version < "3.8"
Requires-Dist: Jinja2
Requires-Dist: requests
Provides-Extra: testing
Requires-Dist: setuptools; extra == "testing"
Requires-Dist: pytest; extra == "testing"
Requires-Dist: pytest-cov; extra == "testing"
Requires-Dist: pytest-mock; extra == "testing"
Requires-Dist: twine; extra == "testing"
Requires-Dist: wheel; extra == "testing"
